counter.v
module counter (input wire clk, 
                input wire rst_n, 
                output reg [3:0] count
);

always @(posedge clk or negedge rst_n) begin
    if (!rst_n) begin
      out <= 4'b0000;
    end 
      else begin
        out <= out + 1b1;
      end
      
    end

endmodule

testbench.v
`timescale 1ns / 1ps  // Sets the time unit to nanoseconds

module counter_tb;

    // 1. Inputs to the counter are regs in the testbench because we control them
    reg clk;
    reg rst_n;

    // 2. Outputs from the counter are wires because we just observe them
    wire [3:0] count;

    // 3. Instantiate (plug in) the counter module we want to test
    counter uut (
        .clk(clk),
        .rst_n(rst_n),
        .count(count)
    );

    // 4. Generate the Clock Signal
    // This constantly toggles the clock every 5 nanoseconds, creating a square wave
    always begin
        #5 clk = ~clk;
    end

    // 5. The Test Sequence
    initial begin
        // Initialize our inputs
        clk = 0;
        rst_n = 0; // Start with reset active (0) to clear the counter

        #15;       // Wait 15 nanoseconds
        rst_n = 1; // Release reset (turn it off) so the counter can start

        #100;      // Let the simulation run for 100 nanoseconds to watch it count
        $finish;   // Stop the simulation
    end

    // 6. This tells the simulator to save the waveform data
    initial begin
        $dumpfile("dump.vcd");
        $dumpvars(0, counter_tb);
    end

endmodule

dump.vcd
$date
	Fri May 22 09:48:11 2026
$end
$version
	Icarus Verilog
$end
$timescale
	1ps
$end
$scope module counter_tb $end
$var wire 4 ! count [3:0] $end
$var reg 1 " clk $end
$var reg 1 # rst_n $end
$scope module uut $end
$var wire 1 " clk $end
$var wire 1 # rst_n $end
$var reg 4 $ count [3:0] $end
$upscope $end
$upscope $end
$enddefinitions $end
$comment Show the parameter values. $end
$dumpall
$end
#0
$dumpvars
b0 $
0#
0"
b0 !
$end
#5000
1"
#10000
0"
#15000
b1 !
b1 $
1"
1#
#20000
0"
#25000
b10 !
b10 $
1"
#30000
0"
#35000
b11 !
b11 $
1"
#40000
0"
#45000
b100 !
b100 $
1"
#50000
0"
#55000
b101 !
b101 $
1"
#60000
0"
#65000
b110 !
b110 $
1"
#70000
0"
#75000
b111 !
b111 $
1"
#80000
0"
#85000
b1000 !
b1000 $
1"
#90000
0"
#95000
b1001 !
b1001 $
1"
#100000
0"
#105000
b1010 !
b1010 $
1"
#110000
0"
#115000
b1011 !
b1011 $
1"
